brilliantai/__init__.py
brilliantai/brilliantai.py
brilliantai_python-0.1.2.dist-info/METADATA
brilliantai_python-0.1.2.dist-info/WHEEL
brilliantai_python-0.1.2.dist-info/licenses/LICENSE
brilliantai_python-0.1.2.dist-info/RECORD
